diskscan/__init__.py
diskscan/chromeos.py
diskscan/cleaner.py
diskscan/cli.py
diskscan/linux.py
diskscan/macos.py
diskscan/windows.py
tests/__init__.py
tests/testcleaner.py
diskscan-0.1.0.dist-info/METADATA
diskscan-0.1.0.dist-info/WHEEL
diskscan-0.1.0.dist-info/entry_points.txt
diskscan-0.1.0.dist-info/top_level.txt
diskscan-0.1.0.dist-info/RECORD
