Metadata-Version: 2.1
Name: diskscan
Version: 0.1.0
Summary: DiskScan - A cross-platform disk cleaner
Home-page: https://github.com/yourusername/diskscan
Author: Your Name
Author-email: your.email@example.com
Classifier: Programming Language :: Python :: 3
Classifier: License :: OSI Approved :: MIT License
Classifier: Operating System :: OS Independent
Requires-Python: >=3.6
